eye_css/__init__.py
eye_css/__main__.py
eye_css/eye_css_generator.py
eye_css/eye_watcher.py
eye_css-0.1.6.dist-info/LICENSE
eye_css-0.1.6.dist-info/METADATA
eye_css-0.1.6.dist-info/WHEEL
eye_css-0.1.6.dist-info/top_level.txt
eye_css-0.1.6.dist-info/RECORD
