Metadata-Version: 2.1
Name: eye-css
Version: 0.1.6
Summary: A dynamic utility-first css library written in python
Home-page: https://github.com/EYE_CSS
Author: Mayowa Obisesan
Author-email: Mayowa Obisesan <mayowaobi74@gmail.com>
License: LICENSE
Project-URL: Homepage, https://github.com/BMayowa/EYE_CSS
Project-URL: Bug Tracker, https://github.com/BMayowa/EYE_CSS/issues
Keywords: Eye CSS,CSS,CSS Library,Utility-First CSS,Python CSS,Web EyeCSS
Classifier: Programming Language :: Python :: 3
Classifier: License :: OSI Approved :: MIT License
Classifier: Operating System :: OS Independent
License-File: LICENSE
Requires-Dist: watchdog (~=2.1.9)
Requires-Dist: PyYAML
